weekdays-0.3.1.dist-info/DESCRIPTION.rst
weekdays-0.3.1.dist-info/top_level.txt
weekdays-0.3.1.dist-info/pydist.json
weekdays-0.3.1.dist-info/zip-safe
weekdays-0.3.1.dist-info/METADATA
weekdays-0.3.1.dist-info/RECORD
weekdays-0.3.1.dist-info/WHEEL
weekdays-0.3.1.dist-info/entry_points.txt
weekdays/helpers.py
weekdays/main.py
weekdays/__init__.py
