Metadata-Version: 2.0
Name: weekdays
Version: 0.3.1
Summary: easily get business days of a range
Home-page: http://bitbucket.org/xcg/weekdays
Author: Florent Aide
Author-email: florent.aide@gmail.com
License: MIT
Keywords: date rrule weekdays business days
Platform: UNKNOWN
Classifier: Development Status :: 3 - Alpha
Classifier: Operating System :: OS Independent
Classifier: Programming Language :: Python
Classifier: License :: OSI Approved :: MIT License
Classifier: Topic :: Software Development :: Libraries :: Python Modules
Requires-Dist: python-dateutil
